{
  "actor": {
    "id": "urn:uuid:01abcdef-2345-6789-abcd-ef0123456789"
  },
  "object": {
    "id": "urn:uuid:abcdef01-2345-6789-abcd-ef0123456789",
    "url": [
      {
        "name": "Canonical",
        "type": "Link",
        "href": "https://islandora.dev/node/1",
        "mediaType": "text/html",
        "rel": "canonical"
      },
      {
        "name": "JSON",
        "type": "Link",
        "href": "https://islandora.dev/node/1?_format=json",
        "mediaType": "application/json",
        "rel": "alternate"
      },
      {
        "name": "JSONLD",
        "type": "Link",
        "href": "https://islandora.dev/node/1?_format=jsonld",
        "mediaType": "application/ld+json",
        "rel": "alternate"
      }
    ],
    "isNewVersion": true
  },
  "attachment": {
    "type": "Object",
    "content": {
      "mimetype": "image/jpeg",
      "args": "-ss 00:00:03.000 -frames 1 -vf scale=100:-2",
      "source_uri": "https://example.com/path/to/file.mp4",
      "destination_uri": "https://example.com/node/1/media/image/2",
      "file_upload_uri": "private://2024-03/thumbnail.jpg"
    },
    "mediaType": "application/json"
  },
  "type": "Activity",
  "summary": "Generate Derivative"
}
